pleio_profile_sync_client/__init__.py
pleio_profile_sync_client/cli.py
pleio_profile_sync_client/lib.py
pleio_profile_sync_client/reader.py
pleio_profile_sync_client-0.1.2.dist-info/LICENSE.md
pleio_profile_sync_client-0.1.2.dist-info/METADATA
pleio_profile_sync_client-0.1.2.dist-info/WHEEL
pleio_profile_sync_client-0.1.2.dist-info/entry_points.txt
pleio_profile_sync_client-0.1.2.dist-info/top_level.txt
pleio_profile_sync_client-0.1.2.dist-info/RECORD
