Metadata-Version: 2.1
Name: pleio-profile-sync-client
Version: 0.1.2
Summary: A Python client that can be used to automatically sync profile information from an identity store to a Pleio subsite.
Home-page: https://gitlab.com/pleio/profile_sync_client
Author: Stichting Pleio
Author-email: support@pleio.nl
License: EUPL-1.2
Platform: UNKNOWN
Requires-Python: >=3.3
Requires-Dist: click
Requires-Dist: requests
